_soundiox.cpython-36m-darwin.so
pysoundio/__init__.py
pysoundio/constants.py
pysoundio/pysoundio.py
pysoundio/structures.py
pysoundio-0.0.2.dist-info/DESCRIPTION.rst
pysoundio-0.0.2.dist-info/METADATA
pysoundio-0.0.2.dist-info/RECORD
pysoundio-0.0.2.dist-info/WHEEL
pysoundio-0.0.2.dist-info/metadata.json
pysoundio-0.0.2.dist-info/top_level.txt
