Metadata-Version: 2.0
Name: pysoundio
Version: 0.0.2
Summary: Python wrapper for libsoundio
Home-page: http://pysoundio.readthedocs.io/en/latest/
Author: Joe Todd
Author-email: joextodd@gmail.com
License: MIT
Download-URL: https://github.com/joextodd/pysoundio/archive/0.0.2.tar.gz
Keywords: audio,sound,stream
Platform: UNKNOWN
Classifier: Development Status :: 3 - Alpha
Classifier: Intended Audience :: Developers
Classifier: Topic :: Software Development :: Build Tools
Classifier: License :: OSI Approved :: MIT License
